turn/__init__.py
turn/client.py
turn/exceptions.py
turn/request_types.py
turn_python-1.0.0.dist-info/METADATA
turn_python-1.0.0.dist-info/WHEEL
turn_python-1.0.0.dist-info/top_level.txt
turn_python-1.0.0.dist-info/RECORD
