Metadata-Version: 2.4
Name: turn-python
Version: 1.0.0
Summary: A python package for the Turn.io WhatsApp API
Home-page: https://github.com/dimagi/turn-python/
Author: Dimagi, inc
Author-email: dev@dimagi.com
Classifier: Programming Language :: Python :: 3
Classifier: License :: OSI Approved :: MIT License
Classifier: Operating System :: OS Independent
Requires-Python: >=3.6
Dynamic: author
Dynamic: author-email
Dynamic: classifier
Dynamic: description
Dynamic: description-content-type
Dynamic: home-page
Dynamic: requires-python
Dynamic: summary
